instructlab_quantize/__init__.py
instructlab_quantize/__main__.py
instructlab_quantize/quantize-aarch64-linux
instructlab_quantize/quantize-arm64-darwin
instructlab_quantize/quantize-x86_64-linux
instructlab_quantize-0.1.0.dist-info/LICENSE
instructlab_quantize-0.1.0.dist-info/METADATA
instructlab_quantize-0.1.0.dist-info/WHEEL
instructlab_quantize-0.1.0.dist-info/top_level.txt
instructlab_quantize-0.1.0.dist-info/RECORD
