Metadata-Version: 2.1
Name: instructlab-quantize
Version: 0.1.0
Summary: Quantize binary for InstructLab
Author-email: Christian Heimes <cheimes@redhat.com>
License: Apache-2.0 AND MIT
Project-URL: source, https://github.com/tiran/instructlab-quantize
Project-URL: issues, https://github.com/tiran/instructlab-quantize/issues
Classifier: Development Status :: 3 - Alpha
Classifier: Environment :: Console
Classifier: License :: OSI Approved :: Apache Software License
Classifier: License :: OSI Approved :: MIT License
Classifier: Operating System :: POSIX :: Linux
Classifier: Operating System :: MacOS :: MacOS X
Classifier: Topic :: Scientific/Engineering :: Artificial Intelligence
Classifier: Programming Language :: Python :: 3
Classifier: Programming Language :: Python :: 3.9
Classifier: Programming Language :: Python :: 3.10
Classifier: Programming Language :: Python :: 3.11
Classifier: Programming Language :: Python :: 3.12
Classifier: Programming Language :: Python :: 3.13
Classifier: Programming Language :: Python :: Implementation :: CPython
Requires-Python: >=3.9
License-File: LICENSE
